gadzooks/__init__.py
gadzooks/build_docs.py
gadzooks/check_format.py
gadzooks/check_version.py
gadzooks/loc_summarize.py
gadzooks/main.py
py_gadzooks-0.2.9.dist-info/METADATA
py_gadzooks-0.2.9.dist-info/WHEEL
py_gadzooks-0.2.9.dist-info/entry_points.txt
py_gadzooks-0.2.9.dist-info/licenses/LICENSE
py_gadzooks-0.2.9.dist-info/RECORD
