Metadata-Version: 2.3
Name: py-gadzooks
Version: 0.2.9
Summary: A collection of code maintenance tools for Python projects, intended to be used within git hooks.
Project-URL: Documentation, https://github.com/jeremander/gadzooks#readme
Project-URL: Issues, https://github.com/jeremander/gadzooks/issues
Project-URL: Source, https://github.com/jeremander/gadzooks
Author-email: Jeremy Silver <jeremys@nessiness.com>
License-Expression: MIT
License-File: LICENSE
Classifier: Programming Language :: Python
Requires-Python: >=3.9
Requires-Dist: radon
